cli.py
epub2sphinx/__init__.py
epub2sphinx/book.py
epub2sphinx/chapter.py
epub2sphinx/constants.py
epub2sphinx/convert.py
epub2sphinx/templates/Makefile
epub2sphinx/templates/conf.py
epub2sphinx/templates/index.rst
epub2sphinx/templates/make.bat
epub2sphinx/templates/makefiles/Makefile
epub2sphinx/templates/makefiles/make.bat
epub2sphinx-0.0.5.dist-info/AUTHORS
epub2sphinx-0.0.5.dist-info/LICENSE
epub2sphinx-0.0.5.dist-info/METADATA
epub2sphinx-0.0.5.dist-info/WHEEL
epub2sphinx-0.0.5.dist-info/entry_points.txt
epub2sphinx-0.0.5.dist-info/top_level.txt
epub2sphinx-0.0.5.dist-info/RECORD
