Metadata-Version: 2.1
Name: epub2sphinx
Version: 0.0.5
Summary: Tool to convert epub to ReST for Sphinx
Home-page: https://github.com/nifey/epub2sphinx
License: MIT
Project-URL: Bug Tracker, https://github.com/nifey/epub2sphinx/issues
Classifier: Programming Language :: Python :: 3
Classifier: License :: OSI Approved :: MIT License
Classifier: Operating System :: OS Independent
Classifier: Environment :: Console
Classifier: Development Status :: 3 - Alpha
Classifier: Topic :: Documentation :: Sphinx
License-File: LICENSE
License-File: AUTHORS
Requires-Dist: click (>=8.0.3)
Requires-Dist: EbookLib (>=0.17.1)
Requires-Dist: pypandoc (>=1.6.4)
Requires-Dist: Jinja2 (>=3.0.3)
Requires-Dist: tqdm (>=4.62.3)
Requires-Dist: sphinx (>=4.4.0)
